vectorcalc/__init__.py
vectorcalc/curves.py
vectorcalc-0.0.2.dist-info/LICENSE
vectorcalc-0.0.2.dist-info/METADATA
vectorcalc-0.0.2.dist-info/WHEEL
vectorcalc-0.0.2.dist-info/top_level.txt
vectorcalc-0.0.2.dist-info/RECORD
