Metadata-Version: 2.1
Name: vectorcalc
Version: 0.0.2
Summary: A small package to do vector calculus.
Author-email: Kenny <admin@kennymoc.xyz>
Project-URL: Homepage, https://github.com/xan3c/vectorcalc
Project-URL: Bug Tracker, https://github.com/xan3c/vectorcalc/issues
Classifier: Programming Language :: Python :: 3
Classifier: License :: OSI Approved :: MIT License
Classifier: Operating System :: OS Independent
Requires-Python: >=3.7
License-File: LICENSE
